examples/__init__.py
examples/ajax_example.py
examples/column_properties_example.py
examples/dictionary_example.py
examples/empty_list_example.py
examples/input_example.py
examples/invalid_data_example.py
examples/pandas_dataframe_example.py
examples/redraw_example.py
examples/simple_example.py
streamlit_datatables_net/__init__.py
streamlit_datatables_net/date_formatter.py
streamlit_datatables_net/mutation_functions.py
streamlit_datatables_net/streamlit_callback.py
streamlit_datatables_net/utility_functions.py
streamlit_datatables_net/frontend/build/asset-manifest.json
streamlit_datatables_net/frontend/build/index.html
streamlit_datatables_net/frontend/build/static/css/main.bdafa3c9.css
streamlit_datatables_net/frontend/build/static/css/main.bdafa3c9.css.map
streamlit_datatables_net/frontend/build/static/js/main.a80f52a3.js
streamlit_datatables_net/frontend/build/static/js/main.a80f52a3.js.LICENSE.txt
streamlit_datatables_net/frontend/build/static/js/main.a80f52a3.js.map
streamlit_datatables_net-0.0.159.dist-info/licenses/LICENSE
streamlit_datatables_net-0.0.159.dist-info/METADATA
streamlit_datatables_net-0.0.159.dist-info/WHEEL
streamlit_datatables_net-0.0.159.dist-info/top_level.txt
streamlit_datatables_net-0.0.159.dist-info/RECORD
