Metadata-Version: 2.4
Name: streamlit-datatables-net
Version: 0.0.159
Summary: Streamlit component for Datatables.net
Home-page: 
Requires-Python: >=3.7
License-File: LICENSE
Requires-Dist: streamlit>=1.34
Provides-Extra: devel
Requires-Dist: wheel; extra == "devel"
Requires-Dist: pytest==7.4.0; extra == "devel"
Requires-Dist: playwright==1.39.0; extra == "devel"
Requires-Dist: requests==2.31.0; extra == "devel"
Requires-Dist: pytest-playwright-snapshot==1.0; extra == "devel"
Requires-Dist: pytest-rerunfailures==12.0; extra == "devel"
Requires-Dist: pyyaml==6.0.1; extra == "devel"
Dynamic: description
Dynamic: description-content-type
Dynamic: license-file
Dynamic: provides-extra
Dynamic: requires-dist
Dynamic: requires-python
Dynamic: summary
